{
  "map_id": "UTE-MAP-PROTOTYPE-V2",
  "description": "Interactive UTE truth topology prototype v2.",
  "nodes": [
    {
      "id": "UTE-FV-0001",
      "title": "Pythagorean Theorem",
      "category": "Geometry",
      "confidence_level": 5,
      "dependencies": [
        "UTE-FV-0002",
        "UTE-FV-0003",
        "UTE-FV-0004",
        "UTE-FV-0006",
        "UTE-FV-0008",
        "UTE-FV-0012"
      ],
      "dependency_centrality": 0,
      "claim": "Pythagorean Theorem is represented as a Core Truth node in the UTE map."
    },
    {
      "id": "UTE-FV-0002",
      "title": "Equality / Identity of Quantity",
      "category": "Logic",
      "confidence_level": 5,
      "dependencies": [],
      "dependency_centrality": 13,
      "claim": "Equality / Identity of Quantity is represented as a Core Truth node in the UTE map."
    },
    {
      "id": "UTE-FV-0003",
      "title": "Counting and Natural Numbers",
      "category": "Arithmetic",
      "confidence_level": 5,
      "dependencies": [
        "UTE-FV-0002"
      ],
      "dependency_centrality": 10,
      "claim": "Counting and Natural Numbers is represented as a Core Truth node in the UTE map."
    },
    {
      "id": "UTE-FV-0004",
      "title": "Addition",
      "category": "Arithmetic",
      "confidence_level": 5,
      "dependencies": [
        "UTE-FV-0002",
        "UTE-FV-0003"
      ],
      "dependency_centrality": 4,
      "claim": "Addition is represented as a Core Truth node in the UTE map."
    },
    {
      "id": "UTE-FV-0005",
      "title": "Subtraction",
      "category": "Arithmetic",
      "confidence_level": 5,
      "dependencies": [
        "UTE-FV-0002",
        "UTE-FV-0003",
        "UTE-FV-0004"
      ],
      "dependency_centrality": 2,
      "claim": "Subtraction is represented as a Core Truth node in the UTE map."
    },
    {
      "id": "UTE-FV-0006",
      "title": "Multiplication",
      "category": "Arithmetic",
      "confidence_level": 5,
      "dependencies": [
        "UTE-FV-0002",
        "UTE-FV-0003",
        "UTE-FV-0004"
      ],
      "dependency_centrality": 4,
      "claim": "Multiplication is represented as a Core Truth node in the UTE map."
    },
    {
      "id": "UTE-FV-0007",
      "title": "Division",
      "category": "Arithmetic",
      "confidence_level": 5,
      "dependencies": [
        "UTE-FV-0002",
        "UTE-FV-0003",
        "UTE-FV-0004",
        "UTE-FV-0006"
      ],
      "dependency_centrality": 2,
      "claim": "Division is represented as a Core Truth node in the UTE map."
    },
    {
      "id": "UTE-FV-0008",
      "title": "Fractions",
      "category": "Arithmetic",
      "confidence_level": 5,
      "dependencies": [
        "UTE-FV-0002",
        "UTE-FV-0003",
        "UTE-FV-0007"
      ],
      "dependency_centrality": 3,
      "claim": "Fractions is represented as a Core Truth node in the UTE map."
    },
    {
      "id": "UTE-FV-0009",
      "title": "Ratio",
      "category": "Arithmetic",
      "confidence_level": 5,
      "dependencies": [
        "UTE-FV-0002",
        "UTE-FV-0003",
        "UTE-FV-0007",
        "UTE-FV-0008"
      ],
      "dependency_centrality": 1,
      "claim": "Ratio is represented as a Core Truth node in the UTE map."
    },
    {
      "id": "UTE-FV-0010",
      "title": "Proportion",
      "category": "Arithmetic",
      "confidence_level": 5,
      "dependencies": [
        "UTE-FV-0002",
        "UTE-FV-0008",
        "UTE-FV-0009"
      ],
      "dependency_centrality": 0,
      "claim": "Proportion is represented as a Core Truth node in the UTE map."
    },
    {
      "id": "UTE-FV-0011",
      "title": "Exponents",
      "category": "Arithmetic",
      "confidence_level": 5,
      "dependencies": [
        "UTE-FV-0002",
        "UTE-FV-0003",
        "UTE-FV-0006"
      ],
      "dependency_centrality": 1,
      "claim": "Exponents is represented as a Core Truth node in the UTE map."
    },
    {
      "id": "UTE-FV-0012",
      "title": "Roots",
      "category": "Arithmetic",
      "confidence_level": 5,
      "dependencies": [
        "UTE-FV-0002",
        "UTE-FV-0006",
        "UTE-FV-0011"
      ],
      "dependency_centrality": 1,
      "claim": "Roots is represented as a Core Truth node in the UTE map."
    },
    {
      "id": "UTE-FV-0013",
      "title": "Negative Numbers",
      "category": "Arithmetic",
      "confidence_level": 5,
      "dependencies": [
        "UTE-FV-0002",
        "UTE-FV-0003",
        "UTE-FV-0005"
      ],
      "dependency_centrality": 0,
      "claim": "Negative Numbers is represented as a Core Truth node in the UTE map."
    },
    {
      "id": "UTE-FV-0014",
      "title": "Approximation",
      "category": "Measurement",
      "confidence_level": 5,
      "dependencies": [
        "UTE-FV-0002",
        "UTE-FV-0003",
        "UTE-FV-0005"
      ],
      "dependency_centrality": 0,
      "claim": "Approximation is represented as a Core Truth node in the UTE map."
    }
  ],
  "edges": [
    {
      "source": "UTE-FV-0001",
      "target": "UTE-FV-0002",
      "type": "depends_on",
      "weight": 1.0
    },
    {
      "source": "UTE-FV-0001",
      "target": "UTE-FV-0003",
      "type": "depends_on",
      "weight": 1.0
    },
    {
      "source": "UTE-FV-0001",
      "target": "UTE-FV-0004",
      "type": "depends_on",
      "weight": 1.0
    },
    {
      "source": "UTE-FV-0001",
      "target": "UTE-FV-0006",
      "type": "depends_on",
      "weight": 1.0
    },
    {
      "source": "UTE-FV-0001",
      "target": "UTE-FV-0008",
      "type": "depends_on",
      "weight": 1.0
    },
    {
      "source": "UTE-FV-0001",
      "target": "UTE-FV-0012",
      "type": "depends_on",
      "weight": 1.0
    },
    {
      "source": "UTE-FV-0003",
      "target": "UTE-FV-0002",
      "type": "depends_on",
      "weight": 1.0
    },
    {
      "source": "UTE-FV-0004",
      "target": "UTE-FV-0002",
      "type": "depends_on",
      "weight": 1.0
    },
    {
      "source": "UTE-FV-0004",
      "target": "UTE-FV-0003",
      "type": "depends_on",
      "weight": 1.0
    },
    {
      "source": "UTE-FV-0005",
      "target": "UTE-FV-0002",
      "type": "depends_on",
      "weight": 1.0
    },
    {
      "source": "UTE-FV-0005",
      "target": "UTE-FV-0003",
      "type": "depends_on",
      "weight": 1.0
    },
    {
      "source": "UTE-FV-0005",
      "target": "UTE-FV-0004",
      "type": "depends_on",
      "weight": 1.0
    },
    {
      "source": "UTE-FV-0006",
      "target": "UTE-FV-0002",
      "type": "depends_on",
      "weight": 1.0
    },
    {
      "source": "UTE-FV-0006",
      "target": "UTE-FV-0003",
      "type": "depends_on",
      "weight": 1.0
    },
    {
      "source": "UTE-FV-0006",
      "target": "UTE-FV-0004",
      "type": "depends_on",
      "weight": 1.0
    },
    {
      "source": "UTE-FV-0007",
      "target": "UTE-FV-0002",
      "type": "depends_on",
      "weight": 1.0
    },
    {
      "source": "UTE-FV-0007",
      "target": "UTE-FV-0003",
      "type": "depends_on",
      "weight": 1.0
    },
    {
      "source": "UTE-FV-0007",
      "target": "UTE-FV-0004",
      "type": "depends_on",
      "weight": 1.0
    },
    {
      "source": "UTE-FV-0007",
      "target": "UTE-FV-0006",
      "type": "depends_on",
      "weight": 1.0
    },
    {
      "source": "UTE-FV-0008",
      "target": "UTE-FV-0002",
      "type": "depends_on",
      "weight": 1.0
    },
    {
      "source": "UTE-FV-0008",
      "target": "UTE-FV-0003",
      "type": "depends_on",
      "weight": 1.0
    },
    {
      "source": "UTE-FV-0008",
      "target": "UTE-FV-0007",
      "type": "depends_on",
      "weight": 1.0
    },
    {
      "source": "UTE-FV-0009",
      "target": "UTE-FV-0002",
      "type": "depends_on",
      "weight": 1.0
    },
    {
      "source": "UTE-FV-0009",
      "target": "UTE-FV-0003",
      "type": "depends_on",
      "weight": 1.0
    },
    {
      "source": "UTE-FV-0009",
      "target": "UTE-FV-0007",
      "type": "depends_on",
      "weight": 1.0
    },
    {
      "source": "UTE-FV-0009",
      "target": "UTE-FV-0008",
      "type": "depends_on",
      "weight": 1.0
    },
    {
      "source": "UTE-FV-0010",
      "target": "UTE-FV-0002",
      "type": "depends_on",
      "weight": 1.0
    },
    {
      "source": "UTE-FV-0010",
      "target": "UTE-FV-0008",
      "type": "depends_on",
      "weight": 1.0
    },
    {
      "source": "UTE-FV-0010",
      "target": "UTE-FV-0009",
      "type": "depends_on",
      "weight": 1.0
    },
    {
      "source": "UTE-FV-0011",
      "target": "UTE-FV-0002",
      "type": "depends_on",
      "weight": 1.0
    },
    {
      "source": "UTE-FV-0011",
      "target": "UTE-FV-0003",
      "type": "depends_on",
      "weight": 1.0
    },
    {
      "source": "UTE-FV-0011",
      "target": "UTE-FV-0006",
      "type": "depends_on",
      "weight": 1.0
    },
    {
      "source": "UTE-FV-0012",
      "target": "UTE-FV-0002",
      "type": "depends_on",
      "weight": 1.0
    },
    {
      "source": "UTE-FV-0012",
      "target": "UTE-FV-0006",
      "type": "depends_on",
      "weight": 1.0
    },
    {
      "source": "UTE-FV-0012",
      "target": "UTE-FV-0011",
      "type": "depends_on",
      "weight": 1.0
    },
    {
      "source": "UTE-FV-0013",
      "target": "UTE-FV-0002",
      "type": "depends_on",
      "weight": 1.0
    },
    {
      "source": "UTE-FV-0013",
      "target": "UTE-FV-0003",
      "type": "depends_on",
      "weight": 1.0
    },
    {
      "source": "UTE-FV-0013",
      "target": "UTE-FV-0005",
      "type": "depends_on",
      "weight": 1.0
    },
    {
      "source": "UTE-FV-0014",
      "target": "UTE-FV-0002",
      "type": "depends_on",
      "weight": 1.0
    },
    {
      "source": "UTE-FV-0014",
      "target": "UTE-FV-0003",
      "type": "depends_on",
      "weight": 1.0
    },
    {
      "source": "UTE-FV-0014",
      "target": "UTE-FV-0005",
      "type": "depends_on",
      "weight": 1.0
    }
  ],
  "visual_encoding": {
    "node_size": "dependency_centrality",
    "node_color": "domain/category",
    "edge_width": "dependency_weight",
    "arrows": "dependency direction",
    "layout": "force_directed"
  }
}